{
	"name": "Excel1",
	"properties": {
		"linkedServiceName": {
			"referenceName": "AzureBlobStorage8",
			"type": "LinkedServiceReference"
		},
		"annotations": [],
		"type": "Excel",
		"typeProperties": {
			"sheetName": "Orders",
			"location": {
				"type": "AzureBlobStorageLocation",
				"fileName": "retailsalesdataset.xlsx",
				"container": "foreachcontainer"
			}
		},
		"schema": [
			{
				"type": "String"
			},
			{
				"type": "String"
			},
			{
				"type": "String"
			},
			{
				"type": "String"
			},
			{
				"type": "String"
			},
			{
				"type": "String"
			},
			{
				"type": "String"
			}
		]
	},
	"type": "Microsoft.DataFactory/factories/datasets"
}