{
	"$schema": "http://schema.management.azure.com/schemas/2015-01-01/deploymentTemplate.json#",
	"contentVersion": "1.0.0.0",
	"parameters": {
		"factoryName": {
			"type": "string",
			"metadata": "Data Factory name",
			"defaultValue": "suvetha-data-factory-practice1"
		},
		"AzureBlobStorage1_connectionString": {
			"type": "secureString",
			"metadata": "Secure string for 'connectionString' of 'AzureBlobStorage1'"
		},
		"AzureBlobStorage2_connectionString": {
			"type": "secureString",
			"metadata": "Secure string for 'connectionString' of 'AzureBlobStorage2'"
		},
		"AzureBlobStorage3_connectionString": {
			"type": "secureString",
			"metadata": "Secure string for 'connectionString' of 'AzureBlobStorage3'"
		},
		"AzureBlobStorage4_connectionString": {
			"type": "secureString",
			"metadata": "Secure string for 'connectionString' of 'AzureBlobStorage4'"
		},
		"AzureBlobStorage5_connectionString": {
			"type": "secureString",
			"metadata": "Secure string for 'connectionString' of 'AzureBlobStorage5'"
		},
		"AzureBlobStorage6_connectionString": {
			"type": "secureString",
			"metadata": "Secure string for 'connectionString' of 'AzureBlobStorage6'"
		},
		"AzureBlobStorage7_connectionString": {
			"type": "secureString",
			"metadata": "Secure string for 'connectionString' of 'AzureBlobStorage7'"
		},
		"AzureBlobStorage8_connectionString": {
			"type": "secureString",
			"metadata": "Secure string for 'connectionString' of 'AzureBlobStorage8'"
		},
		"AzureBlobStorage9_connectionString": {
			"type": "secureString",
			"metadata": "Secure string for 'connectionString' of 'AzureBlobStorage9'"
		},
		"AzureBlobStorageexcel_connectionString": {
			"type": "secureString",
			"metadata": "Secure string for 'connectionString' of 'AzureBlobStorageexcel'"
		},
		"AzureBlobStoragesheet_connectionString": {
			"type": "secureString",
			"metadata": "Secure string for 'connectionString' of 'AzureBlobStoragesheet'"
		},
		"AzureSqlDatabase1_password": {
			"type": "secureString",
			"metadata": "Secure string for 'password' of 'AzureSqlDatabase1'"
		},
		"AzureSqlDatabase2_password": {
			"type": "secureString",
			"metadata": "Secure string for 'password' of 'AzureSqlDatabase2'"
		},
		"AzureSqlDatabaseAssessment_password": {
			"type": "secureString",
			"metadata": "Secure string for 'password' of 'AzureSqlDatabaseAssessment'"
		},
		"SqlServer1_password": {
			"type": "secureString",
			"metadata": "Secure string for 'password' of 'SqlServer1'"
		},
		"linkedService1_connectionString": {
			"type": "secureString",
			"metadata": "Secure string for 'connectionString' of 'linkedService1'"
		},
		"AzureBlobStorageAssessment1_connectionString": {
			"type": "secureString",
			"metadata": "Secure string for 'connectionString' of 'AzureBlobStorageAssessment1'"
		},
		"AzureSqlAssesmentsql_password": {
			"type": "secureString",
			"metadata": "Secure string for 'password' of 'AzureSqlAssesmentsql'"
		},
		"AzureSqlDatabase1_properties_typeProperties_server": {
			"type": "string",
			"defaultValue": "emp-server1.database.windows.net"
		},
		"AzureSqlDatabase1_properties_typeProperties_database": {
			"type": "string",
			"defaultValue": "empdept"
		},
		"AzureSqlDatabase1_properties_typeProperties_userName": {
			"type": "string",
			"defaultValue": "suvetha"
		},
		"AzureSqlDatabase2_properties_typeProperties_server": {
			"type": "string",
			"defaultValue": "emp-server1.database.windows.net"
		},
		"AzureSqlDatabase2_properties_typeProperties_database": {
			"type": "string",
			"defaultValue": "empdept"
		},
		"AzureSqlDatabase2_properties_typeProperties_userName": {
			"type": "string",
			"defaultValue": "suvetha"
		},
		"AzureSqlDatabaseAssessment_properties_typeProperties_server": {
			"type": "string",
			"defaultValue": "emp-server1.database.windows.net"
		},
		"AzureSqlDatabaseAssessment_properties_typeProperties_database": {
			"type": "string",
			"defaultValue": "empdept"
		},
		"AzureSqlDatabaseAssessment_properties_typeProperties_userName": {
			"type": "string",
			"defaultValue": "suvetha"
		},
		"RestService1_properties_typeProperties_url": {
			"type": "string",
			"defaultValue": "https://jsonplaceholder.typicode.com/users"
		},
		"SqlServer1_properties_typeProperties_server": {
			"type": "string",
			"defaultValue": "suvetha"
		},
		"SqlServer1_properties_typeProperties_database": {
			"type": "string",
			"defaultValue": "suvetha"
		},
		"SqlServer1_properties_typeProperties_userName": {
			"type": "string",
			"defaultValue": "suvethaa"
		},
		"AzureSqlAssesmentsql_properties_typeProperties_server": {
			"type": "string",
			"defaultValue": "emp-server1.database.windows.net"
		},
		"AzureSqlAssesmentsql_properties_typeProperties_database": {
			"type": "string",
			"defaultValue": "empdept"
		},
		"AzureSqlAssesmentsql_properties_typeProperties_userName": {
			"type": "string",
			"defaultValue": "suvetha"
		},
		"containerUri": {
			"type": "string",
			"metadata": "URI to storage account containing linked ARM templates"
		},
		"containerSasToken": {
			"type": "string",
			"metadata": "Sas token to storage account containing linked ARM templates"
		}
	},
	"variables": {
		"factoryId": "[concat('Microsoft.DataFactory/factories/', parameters('factoryName'))]"
	},
	"resources": [
		{
			"name": "suvetha-data-factory-practice1_ArmTemplate_0",
			"type": "Microsoft.Resources/deployments",
			"apiVersion": "2024-03-01",
			"properties": {
				"mode": "incremental",
				"templateLink": {
					"uri": "[concat(parameters('containerUri'), '/ArmTemplate_0.json', parameters('containerSasToken'))]",
					"contentVersion": "1.0.0.0"
				},
				"parameters": {
					"factoryName": {
						"value": "[parameters('factoryName')]"
					},
					"AzureBlobStorage1_connectionString": {
						"value": "[parameters('AzureBlobStorage1_connectionString')]"
					},
					"AzureBlobStorage2_connectionString": {
						"value": "[parameters('AzureBlobStorage2_connectionString')]"
					},
					"AzureBlobStorage3_connectionString": {
						"value": "[parameters('AzureBlobStorage3_connectionString')]"
					},
					"AzureBlobStorage4_connectionString": {
						"value": "[parameters('AzureBlobStorage4_connectionString')]"
					},
					"AzureBlobStorage5_connectionString": {
						"value": "[parameters('AzureBlobStorage5_connectionString')]"
					},
					"AzureBlobStorage6_connectionString": {
						"value": "[parameters('AzureBlobStorage6_connectionString')]"
					},
					"AzureBlobStorage7_connectionString": {
						"value": "[parameters('AzureBlobStorage7_connectionString')]"
					},
					"AzureBlobStorage8_connectionString": {
						"value": "[parameters('AzureBlobStorage8_connectionString')]"
					},
					"AzureBlobStorage9_connectionString": {
						"value": "[parameters('AzureBlobStorage9_connectionString')]"
					},
					"AzureBlobStorageexcel_connectionString": {
						"value": "[parameters('AzureBlobStorageexcel_connectionString')]"
					},
					"AzureBlobStoragesheet_connectionString": {
						"value": "[parameters('AzureBlobStoragesheet_connectionString')]"
					},
					"AzureSqlDatabase1_password": {
						"value": "[parameters('AzureSqlDatabase1_password')]"
					},
					"AzureSqlDatabase2_password": {
						"value": "[parameters('AzureSqlDatabase2_password')]"
					},
					"AzureSqlDatabaseAssessment_password": {
						"value": "[parameters('AzureSqlDatabaseAssessment_password')]"
					},
					"SqlServer1_password": {
						"value": "[parameters('SqlServer1_password')]"
					},
					"linkedService1_connectionString": {
						"value": "[parameters('linkedService1_connectionString')]"
					},
					"AzureBlobStorageAssessment1_connectionString": {
						"value": "[parameters('AzureBlobStorageAssessment1_connectionString')]"
					},
					"AzureSqlAssesmentsql_password": {
						"value": "[parameters('AzureSqlAssesmentsql_password')]"
					},
					"AzureSqlDatabase1_properties_typeProperties_server": {
						"value": "[parameters('AzureSqlDatabase1_properties_typeProperties_server')]"
					},
					"AzureSqlDatabase1_properties_typeProperties_database": {
						"value": "[parameters('AzureSqlDatabase1_properties_typeProperties_database')]"
					},
					"AzureSqlDatabase1_properties_typeProperties_userName": {
						"value": "[parameters('AzureSqlDatabase1_properties_typeProperties_userName')]"
					},
					"AzureSqlDatabase2_properties_typeProperties_server": {
						"value": "[parameters('AzureSqlDatabase2_properties_typeProperties_server')]"
					},
					"AzureSqlDatabase2_properties_typeProperties_database": {
						"value": "[parameters('AzureSqlDatabase2_properties_typeProperties_database')]"
					},
					"AzureSqlDatabase2_properties_typeProperties_userName": {
						"value": "[parameters('AzureSqlDatabase2_properties_typeProperties_userName')]"
					},
					"AzureSqlDatabaseAssessment_properties_typeProperties_server": {
						"value": "[parameters('AzureSqlDatabaseAssessment_properties_typeProperties_server')]"
					},
					"AzureSqlDatabaseAssessment_properties_typeProperties_database": {
						"value": "[parameters('AzureSqlDatabaseAssessment_properties_typeProperties_database')]"
					},
					"AzureSqlDatabaseAssessment_properties_typeProperties_userName": {
						"value": "[parameters('AzureSqlDatabaseAssessment_properties_typeProperties_userName')]"
					},
					"RestService1_properties_typeProperties_url": {
						"value": "[parameters('RestService1_properties_typeProperties_url')]"
					},
					"SqlServer1_properties_typeProperties_server": {
						"value": "[parameters('SqlServer1_properties_typeProperties_server')]"
					},
					"SqlServer1_properties_typeProperties_database": {
						"value": "[parameters('SqlServer1_properties_typeProperties_database')]"
					},
					"SqlServer1_properties_typeProperties_userName": {
						"value": "[parameters('SqlServer1_properties_typeProperties_userName')]"
					},
					"AzureSqlAssesmentsql_properties_typeProperties_server": {
						"value": "[parameters('AzureSqlAssesmentsql_properties_typeProperties_server')]"
					},
					"AzureSqlAssesmentsql_properties_typeProperties_database": {
						"value": "[parameters('AzureSqlAssesmentsql_properties_typeProperties_database')]"
					},
					"AzureSqlAssesmentsql_properties_typeProperties_userName": {
						"value": "[parameters('AzureSqlAssesmentsql_properties_typeProperties_userName')]"
					}
				}
			},
			"dependsOn": []
		},
		{
			"name": "suvetha-data-factory-practice1_ArmTemplate_1",
			"type": "Microsoft.Resources/deployments",
			"apiVersion": "2024-03-01",
			"properties": {
				"mode": "incremental",
				"templateLink": {
					"uri": "[concat(parameters('containerUri'), '/ArmTemplate_1.json', parameters('containerSasToken'))]",
					"contentVersion": "1.0.0.0"
				},
				"parameters": {
					"factoryName": {
						"value": "[parameters('factoryName')]"
					}
				}
			},
			"dependsOn": [
				"[resourceId('Microsoft.Resources/deployments', 'suvetha-data-factory-practice1_ArmTemplate_0')]"
			]
		},
		{
			"name": "suvetha-data-factory-practice1_ArmTemplate_2",
			"type": "Microsoft.Resources/deployments",
			"apiVersion": "2024-03-01",
			"properties": {
				"mode": "incremental",
				"templateLink": {
					"uri": "[concat(parameters('containerUri'), '/ArmTemplate_2.json', parameters('containerSasToken'))]",
					"contentVersion": "1.0.0.0"
				},
				"parameters": {
					"factoryName": {
						"value": "[parameters('factoryName')]"
					}
				}
			},
			"dependsOn": [
				"[resourceId('Microsoft.Resources/deployments', 'suvetha-data-factory-practice1_ArmTemplate_1')]"
			]
		}
	]
}